<annotation verified="yes">
	<folder>56f8e7c9025e9511002786d1</folder>
	<filename>56f8e7c9025e9511002786d1_1603729510.jpg</filename>
	<path>E:\doAnCuoiKiML\label\56f8e7c9025e9511002786d1\56f8e7c9025e9511002786d1_1603729510.jpg</path>
	<source>
		<database>Unknown</database>
	</source>
	<size>
		<width>1080</width>
		<height>720</height>
		<depth>3</depth>
	</size>
	<segmented>0</segmented>
	<object>
		<name>6</name>
		<pose>Unspecified</pose>
		<truncated>0</truncated>
		<difficult>0</difficult>
		<bndbox>
			<xmin>362</xmin>
			<ymin>216</ymin>
			<xmax>410</xmax>
			<ymax>271</ymax>
		</bndbox>
	</object>
	<object>
		<name>11</name>
		<pose>Unspecified</pose>
		<truncated>0</truncated>
		<difficult>0</difficult>
		<bndbox>
			<xmin>179</xmin>
			<ymin>290</ymin>
			<xmax>340</xmax>
			<ymax>546</ymax>
		</bndbox>
	</object>
</annotation>
